Metadata-Version: 2.1
Name: shallowpavlov
Version: 0.0.2
Summary: An open source library for building end-to-end dialog systems and training chatbots.
Home-page: https://github.com/deepmipt/DeepPavlov
Download-URL: https://github.com/deepmipt/DeepPavlov/archive/1.0.0rc1.tar.gz
Author: Neural Networks and Deep Learning lab, MIPT
Author-email: info@deeppavlov.ai
License: Apache License, Version 2.0
Keywords: NLP,NER,SQUAD,Intents,Chatbot
License-File: LICENSE
Requires-Dist: aio-pika (<6.9.0,>=3.2.2)
Requires-Dist: fastapi (<0.78.0,>=0.47.0)
Requires-Dist: filelock (<3.8.0,>=3.0.0)
Requires-Dist: nltk (<3.8.0,>=3.2.5)
Requires-Dist: numpy
Requires-Dist: overrides (==4.1.2)
Requires-Dist: pandas (<1.5.0,>=1.0.0)
Requires-Dist: prometheus-client (<0.15.0,>=0.13.0)
Requires-Dist: pydantic
Requires-Dist: pymorphy2 (==0.9.1)
Requires-Dist: pybind11 (==2.2.4)
Requires-Dist: requests (<3.0.0,>=2.19.0)
Requires-Dist: scikit-learn (<1.1.0,>=0.24)
Requires-Dist: scipy (<1.9.0)
Requires-Dist: tqdm (<4.65.0,>=4.42.0)
Requires-Dist: uvicorn (<0.19.0,>=0.13.0)
Provides-Extra: docs
Requires-Dist: sphinx (==3.5.4) ; extra == 'docs'
Requires-Dist: sphinx-rtd-theme (==0.5.2) ; extra == 'docs'
Requires-Dist: nbsphinx (==0.8.4) ; extra == 'docs'
Requires-Dist: ipykernel (==5.5.4) ; extra == 'docs'
Requires-Dist: jinja2 (<=3.0.3) ; extra == 'docs'
Provides-Extra: s3
Requires-Dist: boto3 ; extra == 's3'
Provides-Extra: tests
Requires-Dist: flake8 ; extra == 'tests'
Requires-Dist: pytest ; extra == 'tests'
Requires-Dist: pytest-instafail ; extra == 'tests'
Requires-Dist: pexpect ; extra == 'tests'
